{
  "name": "WorklogDependencies",
  "options": {
    "idInjection": false,
    "mysql": {
      "schema": "DS_Inclutec_Bitacoras_v3",
      "table": "WorklogDependencies"
    },
    "relations": {
      "fkWorklogdependencies1rel": {
        "model": "Projects",
        "type": "belongsTo",
        "foreignKey": "idProjectsFk"
      },
      "fkWorklogdependencies2rel": {
        "model": "Phases",
        "type": "belongsTo",
        "foreignKey": "idPhaseFk"
      },
      "fkWorklogdependencies3rel": {
        "model": "Activities",
        "type": "belongsTo",
        "foreignKey": "idActivityFk"
      },
      "fkWorklogdependencies4rel": {
        "model": "Task",
        "type": "belongsTo",
        "foreignKey": "idTaskFk"
      }
    }
  },
  "properties": {
    "idWorklogDependenciesPk": {
      "type": "Number",
      "required": true,
      "length": null,
      "precision": 10,
      "scale": 0,
      "id": 1,
      "mysql": {
        "columnName": "idWorklogDependencies_pk",
        "dataType": "int",
        "dataLength": null,
        "dataPrecision": 10,
        "dataScale": 0,
        "nullable": "N"
      }
    },
    "idProjectsFk": {
      "type": "Number",
      "required": true,
      "length": null,
      "precision": 10,
      "scale": 0,
      "mysql": {
        "columnName": "idProjects_fk",
        "dataType": "int",
        "dataLength": null,
        "dataPrecision": 10,
        "dataScale": 0,
        "nullable": "N"
      }
    },
    "idPhaseFk": {
      "type": "Number",
      "required": true,
      "length": null,
      "precision": 10,
      "scale": 0,
      "mysql": {
        "columnName": "idPhase_fk",
        "dataType": "int",
        "dataLength": null,
        "dataPrecision": 10,
        "dataScale": 0,
        "nullable": "N"
      }
    },
    "idActivityFk": {
      "type": "Number",
      "required": true,
      "length": null,
      "precision": 10,
      "scale": 0,
      "mysql": {
        "columnName": "idActivity_fk",
        "dataType": "int",
        "dataLength": null,
        "dataPrecision": 10,
        "dataScale": 0,
        "nullable": "N"
      }
    },
    "idTaskFk": {
      "type": "Number",
      "required": false,
      "length": null,
      "precision": 10,
      "scale": 0,
      "mysql": {
        "columnName": "idTask_fk",
        "dataType": "int",
        "dataLength": null,
        "dataPrecision": 10,
        "dataScale": 0,
        "nullable": "N"
      }
    },
    "startDate": {
      "type": "Date",
      "required": false,
      "length": null,
      "precision": null,
      "scale": null,
      "mysql": {
        "columnName": "startDate",
        "dataType": "datetime",
        "dataLength": null,
        "dataPrecision": null,
        "dataScale": null,
        "nullable": "N"
      }
    },
    "endDate": {
      "type": "Date",
      "required": false,
      "length": null,
      "precision": null,
      "scale": null,
      "mysql": {
        "columnName": "endDate",
        "dataType": "datetime",
        "dataLength": null,
        "dataPrecision": null,
        "dataScale": null,
        "nullable": "N"
      }
    },
    "description": {
      "type": "String",
      "required": false,
      "length": 250,
      "precision": null,
      "scale": null,
      "mysql": {
        "columnName": "description",
        "dataType": "varchar",
        "dataLength": 250,
        "dataPrecision": null,
        "dataScale": null,
        "nullable": "N"
      }
    },
    "spentTime": {
      "type": "Number",
      "required": false,
      "length": null,
      "precision": 12,
      "scale": null,
      "mysql": {
        "columnName": "spentTime",
        "dataType": "float",
        "dataLength": null,
        "dataPrecision": 12,
        "dataScale": null,
        "nullable": "N"
      }
    },
    "modality": {
      "type": "Number",
      "required": false,
      "length": null,
      "precision": 12,
      "scale": null,
      "mysql": {
        "columnName": "modality",
        "dataType": "int",
        "dataLength": null,
        "dataPrecision": 12,
        "dataScale": null,
        "nullable": "N"
      }
    },
    "status": {
      "type": "Number",
      "required": true,
      "length": null,
      "precision": 10,
      "scale": 0,
      "mysql": {
        "columnName": "status",
        "dataType": "int",
        "dataLength": null,
        "dataPrecision": 10,
        "dataScale": 0,
        "nullable": "N"
      }
    }
  }
}
